README.md
setup.py
trackupdates/__init__.py
trackupdates/byr_util.py
trackupdates/database.py
trackupdates/server.py
trackupdates/trackupdates.py
trackupdates/utils.py
trackupdates.egg-info/PKG-INFO
trackupdates.egg-info/SOURCES.txt
trackupdates.egg-info/dependency_links.txt
trackupdates.egg-info/entry_points.txt
trackupdates.egg-info/requires.txt
trackupdates.egg-info/top_level.txt