Metadata-Version: 1.0
Name: trackupdates
Version: 0.0.9
Summary: A simple yaml-based xpath crawler and esay tracking site updates.
Home-page: https://github.com/ZhuPeng/trackupdates
Author: ZhuPeng
Author-email: zhupengbupt@gmail.com
License: MIT License
Platform: UNKNOWN
